aternosapi/__init__.py
AternosAPI-1.2.0.dist-info/LICENSE
AternosAPI-1.2.0.dist-info/METADATA
AternosAPI-1.2.0.dist-info/WHEEL
AternosAPI-1.2.0.dist-info/top_level.txt
AternosAPI-1.2.0.dist-info/RECORD
