Metadata-Version: 2.1
Name: AternosAPI
Version: 1.2.0
Summary: A Python Aternos API
Home-page: https://github.com/Duerocraft/AternosAPI
License: GNU
Platform: UNKNOWN
Classifier: License :: OSI Approved :: GNU General Public License v3 (GPLv3)
Classifier: Programming Language :: Python :: 3.6
Classifier: Programming Language :: Python :: 3.7
Classifier: Programming Language :: Python :: 3.8
Requires-Python: >=3.6
Requires-Dist: requests
Requires-Dist: bs4
